spaudio.py
spplugin.py
_spaudio/__init__.py
_spaudio/_spaudio_c.cpython-310-darwin.so
_spaudio/spaudio_c.py
_spplugin/__init__.py
_spplugin/_spplugin_c.cpython-310-darwin.so
_spplugin/spplugin_c.py
_spplugins/__init__.py
_spplugins/mac64/input_aiff.bundle/Contents/Info.plist
_spplugins/mac64/input_aiff.bundle/Contents/MacOS/input_aiff
_spplugins/mac64/input_aiff.bundle/Contents/Resources/English.lproj/InfoPlist.strings
_spplugins/mac64/input_alac.bundle/Contents/Info.plist
_spplugins/mac64/input_alac.bundle/Contents/MacOS/input_alac
_spplugins/mac64/input_alac.bundle/Contents/Resources/English.lproj/InfoPlist.strings
_spplugins/mac64/input_caf.bundle/Contents/Info.plist
_spplugins/mac64/input_caf.bundle/Contents/MacOS/input_caf
_spplugins/mac64/input_caf.bundle/Contents/Resources/English.lproj/InfoPlist.strings
_spplugins/mac64/input_flac.bundle/Contents/Info.plist
_spplugins/mac64/input_flac.bundle/Contents/MacOS/input_flac
_spplugins/mac64/input_flac.bundle/Contents/Resources/English.lproj/InfoPlist.strings
_spplugins/mac64/input_monkey.bundle/Contents/Info.plist
_spplugins/mac64/input_monkey.bundle/Contents/MacOS/input_monkey
_spplugins/mac64/input_mpeg.bundle/Contents/Info.plist
_spplugins/mac64/input_mpeg.bundle/Contents/MacOS/input_mpeg
_spplugins/mac64/input_mpeg.bundle/Contents/Resources/English.lproj/InfoPlist.strings
_spplugins/mac64/input_nist.bundle/Contents/Info.plist
_spplugins/mac64/input_nist.bundle/Contents/MacOS/input_nist
_spplugins/mac64/input_nist.bundle/Contents/Resources/English.lproj/InfoPlist.strings
_spplugins/mac64/input_ogg.bundle/Contents/Info.plist
_spplugins/mac64/input_ogg.bundle/Contents/MacOS/input_ogg
_spplugins/mac64/input_ogg.bundle/Contents/Resources/English.lproj/InfoPlist.strings
_spplugins/mac64/input_raw.bundle/Contents/Info.plist
_spplugins/mac64/input_raw.bundle/Contents/MacOS/input_raw
_spplugins/mac64/input_raw.bundle/Contents/Resources/English.lproj/InfoPlist.strings
spaudio-0.7.18.dist-info/LICENSE.txt
spaudio-0.7.18.dist-info/METADATA
spaudio-0.7.18.dist-info/WHEEL
spaudio-0.7.18.dist-info/top_level.txt
spaudio-0.7.18.dist-info/RECORD
