Metadata-Version: 2.1
Name: spaudio
Version: 0.7.18
Summary: spAudio audio I/O library
Home-page: https://www-ie.meijo-u.ac.jp/labs/rj001/spLibs/python/spAudio/en/index.html
Author: Hideki Banno
Author-email: banno@meijo-u.ac.jp
License: MIT
Keywords: audio,sound,play,record,I/O,file,capture,wav,aiff,caf,ogg,mp3,flac,alac,python,library
Platform: posix
Platform: nt
Classifier: Development Status :: 4 - Beta
Classifier: Intended Audience :: Developers
Classifier: Intended Audience :: Education
Classifier: Intended Audience :: Science/Research
Classifier: License :: OSI Approved :: MIT License
Classifier: Operating System :: MacOS :: MacOS X
Classifier: Operating System :: Microsoft :: Windows
Classifier: Operating System :: POSIX :: Linux
Classifier: Programming Language :: Python
Classifier: Programming Language :: Python :: 3
Classifier: Topic :: Multimedia :: Sound/Audio
Classifier: Topic :: Multimedia :: Sound/Audio :: Analysis
Classifier: Topic :: Multimedia :: Sound/Audio :: Capture/Recording
Classifier: Topic :: Multimedia :: Sound/Audio :: Conversion
Classifier: Topic :: Software Development :: Libraries :: Python Modules
Provides-Extra: numpy
Requires-Dist: numpy ; extra == 'numpy'
